hko/__init__.py
hko-0.3.1.dist-info/LICENSE
hko-0.3.1.dist-info/METADATA
hko-0.3.1.dist-info/WHEEL
hko-0.3.1.dist-info/RECORD
