Metadata-Version: 2.1
Name: hko
Version: 0.3.1
Summary: An unofficial Python wrapper for public API of Hong Kong Observatory
Home-page: https://github.com/MisterCommand/python-hko
License: MIT
Keywords: hko,weather
Author: MisterCommand
Author-email: anthony.h@gmail.com
Requires-Python: >=3.7,<4.0
Classifier: License :: OSI Approved :: MIT License
Classifier: Programming Language :: Python :: 3
Classifier: Programming Language :: Python :: 3.7
Classifier: Programming Language :: Python :: 3.8
Classifier: Programming Language :: Python :: 3.9
Classifier: Programming Language :: Python :: 3.10
Classifier: Programming Language :: Python :: 3.11
Requires-Dist: aiohttp (>=3.7.4,<4.0.0)
Project-URL: Repository, https://github.com/MisterCommand/python-hko
